README.txt
setup.py
docs/HISTORY.txt
docs/INSTALL.txt
docs/LICENSE.GPL
docs/LICENSE.txt
lineage/__init__.py
lineage.proxyprops.egg-info/PKG-INFO
lineage.proxyprops.egg-info/SOURCES.txt
lineage.proxyprops.egg-info/dependency_links.txt
lineage.proxyprops.egg-info/namespace_packages.txt
lineage.proxyprops.egg-info/not-zip-safe
lineage.proxyprops.egg-info/requires.txt
lineage.proxyprops.egg-info/top_level.txt
lineage/proxyprops/README.txt
lineage/proxyprops/__init__.py
lineage/proxyprops/configure.zcml
lineage/proxyprops/subscribers.py
lineage/proxyprops/tests.py