Metadata-Version: 1.0
Name: lineage.proxyprops
Version: 0.1
Summary: Small wrapper package to add support for collective.proxyprops
Home-page: http://svn.plone.org/svn/collective/lineage.proxyprops
Author: Six Feet Up, Inc.
Author-email: info@sixfeetup.com
License: GPL
Platform: UNKNOWN
Classifier: Framework :: Plone
Classifier: Programming Language :: Python
Classifier: Topic :: Software Development :: Libraries :: Python Modules
